rocket_moea/__init__.py
rocket_moea/fronts/__init__.py
rocket_moea/fronts/fronts.py
rocket_moea/fronts/test_fronts.py
rocket_moea/helpers/__init__.py
rocket_moea/helpers/reference_vectors.py
rocket_moea/helpers/test_reference_vectors.py
rocket_moea-0.1.dist-info/METADATA
rocket_moea-0.1.dist-info/WHEEL
rocket_moea-0.1.dist-info/top_level.txt
rocket_moea-0.1.dist-info/RECORD
