Metadata-Version: 2.1
Name: rocket-moea
Version: 0.1
Summary: A framework to develop evolutionary algorithms
Home-page: UNKNOWN
Author: Auraham Camacho
Author-email: auraham.cg@gmail.com
License: MIT
Platform: UNKNOWN
